client_analyzer/__init__.py
client_analyzer/__main__.py
client_analyzer/client_analyzer.py
client_analyzer_kolya_super-0.1.4.dist-info/METADATA
client_analyzer_kolya_super-0.1.4.dist-info/WHEEL
client_analyzer_kolya_super-0.1.4.dist-info/entry_points.txt
client_analyzer_kolya_super-0.1.4.dist-info/top_level.txt
client_analyzer_kolya_super-0.1.4.dist-info/RECORD
