Metadata-Version: 2.1
Name: client_analyzer_kolya_super
Version: 0.1.4
Summary: Krutoi packege
Author: Nikolai
Author-email: kolaleuhin@gmail.com
